pyLOT/__init__.py
pyLOT/barycenters.py
pyLOT/classifier.py
pyLOT/embed.py
pyLOT/reduction.py
pyLOT/tutorial_data_generation.py
pylotlib-0.1.4.dist-info/METADATA
pylotlib-0.1.4.dist-info/WHEEL
pylotlib-0.1.4.dist-info/top_level.txt
pylotlib-0.1.4.dist-info/RECORD
