Metadata-Version: 2.4
Name: pyLOTlib
Version: 0.1.4
Summary: PyLOT provides general functionality for applying out-of-the-box machine learning methods to point-cloud-valued data or, more generally, measure-valued data.  PyLOT allows the user to embed, classify, dimension reduce, and generate data.
Home-page: https://github.com/ACloninger/pyLOT
Author: Alex Cloninger
Author-email: acloninger@ucsd.edu
Classifier: Programming Language :: Python :: 3
Classifier: License :: OSI Approved :: MIT License
Classifier: Operating System :: OS Independent
Requires-Python: >=3.6
Requires-Dist: numpy
Requires-Dist: imbalanced-learn
Requires-Dist: scikit-learn
Requires-Dist: tensorflow
Requires-Dist: matplotlib
Requires-Dist: pot
Dynamic: author
Dynamic: author-email
Dynamic: classifier
Dynamic: description
Dynamic: description-content-type
Dynamic: home-page
Dynamic: requires-dist
Dynamic: requires-python
Dynamic: summary
